gradient_cli-0.1.9.dist-info/METADATA
gradient_cli-0.1.9.dist-info/WHEEL
gradient_cli-0.1.9.dist-info/licenses/LICENSE
gradient_cli/__init__.py
gradient_cli-0.1.9.dist-info/RECORD
