Metadata-Version: 2.1
Name: gradient-cli
Version: 0.1.9
Summary: A CLI for maxludden/maxgradient
Author-Email: maxludden <dev@maxludden.com>, Max Ludden <dev@maxludden.com>
License: MIT
Requires-Python: >=3.11
Requires-Dist: rich>=13.5.3
Requires-Dist: nptyping>=2.5.0
Requires-Dist: numpy>=1.25.0
Requires-Dist: lorem-text>=2.1
Requires-Dist: typer[all]>=0.9.0
Requires-Dist: python-dotenv[cli]>=1.0.0
Requires-Dist: loguru>=0.7.2
Requires-Dist: mongoengine>=0.27.0
Requires-Dist: PyYAML>=6.0.1
Requires-Dist: maxgradient>=0.1.9
Requires-Dist: pydantic>=2.3.0
Requires-Dist: sh>=2.0.6
